{"v":3,"stories":{"vrxbutton-about--docs":{"id":"vrxbutton-about--docs","title":"VrxButton/About","name":"Docs","importPath":"./src/components/VrxButton/VrxButton.mdx","storiesImports":[],"tags":["unattached-mdx","docs"],"kind":"VrxButton/About","story":"Docs","parameters":{"__id":"vrxbutton-about--docs","docsOnly":true,"fileName":"./src/components/VrxButton/VrxButton.mdx"}},"vrxbuttonsgroup-about--docs":{"id":"vrxbuttonsgroup-about--docs","title":"VrxButtonsGroup/About","name":"Docs","importPath":"./src/components/VrxButtonsGroup/VrxButtonsGroup.mdx","storiesImports":[],"tags":["unattached-mdx","docs"],"kind":"VrxButtonsGroup/About","story":"Docs","parameters":{"__id":"vrxbuttonsgroup-about--docs","docsOnly":true,"fileName":"./src/components/VrxButtonsGroup/VrxButtonsGroup.mdx"}},"vrxgrid-about--docs":{"id":"vrxgrid-about--docs","title":"VrxGrid/About","name":"Docs","importPath":"./src/components/VrxGrid/VrxGrid.mdx","storiesImports":[],"tags":["unattached-mdx","docs"],"kind":"VrxGrid/About","story":"Docs","parameters":{"__id":"vrxgrid-about--docs","docsOnly":true,"fileName":"./src/components/VrxGrid/VrxGrid.mdx"}},"vrxicon-about--docs":{"id":"vrxicon-about--docs","title":"VrxIcon/About","name":"Docs","importPath":"./src/components/VrxIcon/VrxIcon.mdx","storiesImports":[],"tags":["unattached-mdx","docs"],"kind":"VrxIcon/About","story":"Docs","parameters":{"__id":"vrxicon-about--docs","docsOnly":true,"fileName":"./src/components/VrxIcon/VrxIcon.mdx"}},"vrxinput-about--docs":{"id":"vrxinput-about--docs","title":"VrxInput/About","name":"Docs","importPath":"./src/components/VrxInput/VrxInput.mdx","storiesImports":[],"tags":["unattached-mdx","docs"],"kind":"VrxInput/About","story":"Docs","parameters":{"__id":"vrxinput-about--docs","docsOnly":true,"fileName":"./src/components/VrxInput/VrxInput.mdx"}},"vrxnavbar-about--docs":{"id":"vrxnavbar-about--docs","title":"VrxNavbar/About","name":"Docs","importPath":"./src/components/VrxNavbar/VrxNavbar.mdx","storiesImports":[],"tags":["unattached-mdx","docs"],"kind":"VrxNavbar/About","story":"Docs","parameters":{"__id":"vrxnavbar-about--docs","docsOnly":true,"fileName":"./src/components/VrxNavbar/VrxNavbar.mdx"}},"vrxselect-about--docs":{"id":"vrxselect-about--docs","title":"VrxSelect/About","name":"Docs","importPath":"./src/components/VrxSelect/VrxSelect.mdx","storiesImports":[],"tags":["unattached-mdx","docs"],"kind":"VrxSelect/About","story":"Docs","parameters":{"__id":"vrxselect-about--docs","docsOnly":true,"fileName":"./src/components/VrxSelect/VrxSelect.mdx"}},"vrxtoggle-about--docs":{"id":"vrxtoggle-about--docs","title":"VrxToggle/About","name":"Docs","importPath":"./src/components/VrxToggle/VrxToggle.mdx","storiesImports":[],"tags":["unattached-mdx","docs"],"kind":"VrxToggle/About","story":"Docs","parameters":{"__id":"vrxtoggle-about--docs","docsOnly":true,"fileName":"./src/components/VrxToggle/VrxToggle.mdx"}},"vrxbutton--docs":{"id":"vrxbutton--docs","title":"VrxButton","name":"Docs","importPath":"./src/components/VrxButton/VrxButton.stories.ts","tags":["autodocs","docs"],"storiesImports":[],"kind":"VrxButton","story":"Docs","parameters":{"__id":"vrxbutton--docs","docsOnly":true,"fileName":"./src/components/VrxButton/VrxButton.stories.ts"}},"vrxbutton--primary":{"id":"vrxbutton--primary","title":"VrxButton","name":"Primary","importPath":"./src/components/VrxButton/VrxButton.stories.ts","tags":["autodocs","story"],"kind":"VrxButton","story":"Primary","parameters":{"__id":"vrxbutton--primary","docsOnly":false,"fileName":"./src/components/VrxButton/VrxButton.stories.ts"}},"vrxbutton--prefix":{"id":"vrxbutton--prefix","title":"VrxButton","name":"Prefix","importPath":"./src/components/VrxButton/VrxButton.stories.ts","tags":["autodocs","story"],"kind":"VrxButton","story":"Prefix","parameters":{"__id":"vrxbutton--prefix","docsOnly":false,"fileName":"./src/components/VrxButton/VrxButton.stories.ts"}},"vrxbutton--suffix":{"id":"vrxbutton--suffix","title":"VrxButton","name":"Suffix","importPath":"./src/components/VrxButton/VrxButton.stories.ts","tags":["autodocs","story"],"kind":"VrxButton","story":"Suffix","parameters":{"__id":"vrxbutton--suffix","docsOnly":false,"fileName":"./src/components/VrxButton/VrxButton.stories.ts"}},"vrxbutton--both":{"id":"vrxbutton--both","title":"VrxButton","name":"Both","importPath":"./src/components/VrxButton/VrxButton.stories.ts","tags":["autodocs","story"],"kind":"VrxButton","story":"Both","parameters":{"__id":"vrxbutton--both","docsOnly":false,"fileName":"./src/components/VrxButton/VrxButton.stories.ts"}},"vrxbuttonsgroup--docs":{"id":"vrxbuttonsgroup--docs","title":"VrxButtonsGroup","name":"Docs","importPath":"./src/components/VrxButtonsGroup/VrxButtonsGroup.stories.ts","tags":["autodocs","docs"],"storiesImports":[],"kind":"VrxButtonsGroup","story":"Docs","parameters":{"__id":"vrxbuttonsgroup--docs","docsOnly":true,"fileName":"./src/components/VrxButtonsGroup/VrxButtonsGroup.stories.ts"}},"vrxbuttonsgroup--primary":{"id":"vrxbuttonsgroup--primary","title":"VrxButtonsGroup","name":"Primary","importPath":"./src/components/VrxButtonsGroup/VrxButtonsGroup.stories.ts","tags":["autodocs","story"],"kind":"VrxButtonsGroup","story":"Primary","parameters":{"__id":"vrxbuttonsgroup--primary","docsOnly":false,"fileName":"./src/components/VrxButtonsGroup/VrxButtonsGroup.stories.ts"}},"vrxbuttonsgroup--icon":{"id":"vrxbuttonsgroup--icon","title":"VrxButtonsGroup","name":"Icon","importPath":"./src/components/VrxButtonsGroup/VrxButtonsGroup.stories.ts","tags":["autodocs","story"],"kind":"VrxButtonsGroup","story":"Icon","parameters":{"__id":"vrxbuttonsgroup--icon","docsOnly":false,"fileName":"./src/components/VrxButtonsGroup/VrxButtonsGroup.stories.ts"}},"vrxgrid--docs":{"id":"vrxgrid--docs","title":"VrxGrid","name":"Docs","importPath":"./src/components/VrxGrid/VrxGrid.stories.ts","tags":["autodocs","docs"],"storiesImports":[],"kind":"VrxGrid","story":"Docs","parameters":{"__id":"vrxgrid--docs","docsOnly":true,"fileName":"./src/components/VrxGrid/VrxGrid.stories.ts"}},"vrxgrid--primary":{"id":"vrxgrid--primary","title":"VrxGrid","name":"Primary","importPath":"./src/components/VrxGrid/VrxGrid.stories.ts","tags":["autodocs","story"],"kind":"VrxGrid","story":"Primary","parameters":{"__id":"vrxgrid--primary","docsOnly":false,"fileName":"./src/components/VrxGrid/VrxGrid.stories.ts"}},"vrxgrid--filtrable":{"id":"vrxgrid--filtrable","title":"VrxGrid","name":"Filtrable","importPath":"./src/components/VrxGrid/VrxGrid.stories.ts","tags":["autodocs","story"],"kind":"VrxGrid","story":"Filtrable","parameters":{"__id":"vrxgrid--filtrable","docsOnly":false,"fileName":"./src/components/VrxGrid/VrxGrid.stories.ts"}},"vrxgrid--selectable":{"id":"vrxgrid--selectable","title":"VrxGrid","name":"Selectable","importPath":"./src/components/VrxGrid/VrxGrid.stories.ts","tags":["autodocs","story"],"kind":"VrxGrid","story":"Selectable","parameters":{"__id":"vrxgrid--selectable","docsOnly":false,"fileName":"./src/components/VrxGrid/VrxGrid.stories.ts"}},"vrxgrid--multiselectable":{"id":"vrxgrid--multiselectable","title":"VrxGrid","name":"Multiselectable","importPath":"./src/components/VrxGrid/VrxGrid.stories.ts","tags":["autodocs","story"],"kind":"VrxGrid","story":"Multiselectable","parameters":{"__id":"vrxgrid--multiselectable","docsOnly":false,"fileName":"./src/components/VrxGrid/VrxGrid.stories.ts"}},"vrxgrid--editable":{"id":"vrxgrid--editable","title":"VrxGrid","name":"Editable","importPath":"./src/components/VrxGrid/VrxGrid.stories.ts","tags":["autodocs","story"],"kind":"VrxGrid","story":"Editable","parameters":{"__id":"vrxgrid--editable","docsOnly":false,"fileName":"./src/components/VrxGrid/VrxGrid.stories.ts"}},"vrxgrid--static-content":{"id":"vrxgrid--static-content","title":"VrxGrid","name":"Static Content","importPath":"./src/components/VrxGrid/VrxGrid.stories.ts","tags":["autodocs","story"],"kind":"VrxGrid","story":"Static Content","parameters":{"__id":"vrxgrid--static-content","docsOnly":false,"fileName":"./src/components/VrxGrid/VrxGrid.stories.ts"}},"vrxgrid--colspan":{"id":"vrxgrid--colspan","title":"VrxGrid","name":"Colspan","importPath":"./src/components/VrxGrid/VrxGrid.stories.ts","tags":["autodocs","story"],"kind":"VrxGrid","story":"Colspan","parameters":{"__id":"vrxgrid--colspan","docsOnly":false,"fileName":"./src/components/VrxGrid/VrxGrid.stories.ts"}},"vrxicon--docs":{"id":"vrxicon--docs","title":"VrxIcon","name":"Docs","importPath":"./src/components/VrxIcon/VrxIcon.stories.ts","tags":["autodocs","docs"],"storiesImports":[],"kind":"VrxIcon","story":"Docs","parameters":{"__id":"vrxicon--docs","docsOnly":true,"fileName":"./src/components/VrxIcon/VrxIcon.stories.ts"}},"vrxicon--primary":{"id":"vrxicon--primary","title":"VrxIcon","name":"Primary","importPath":"./src/components/VrxIcon/VrxIcon.stories.ts","tags":["autodocs","story"],"kind":"VrxIcon","story":"Primary","parameters":{"__id":"vrxicon--primary","docsOnly":false,"fileName":"./src/components/VrxIcon/VrxIcon.stories.ts"}},"vrxinput--docs":{"id":"vrxinput--docs","title":"VrxInput","name":"Docs","importPath":"./src/components/VrxInput/VrxInput.stories.ts","tags":["autodocs","docs"],"storiesImports":[],"kind":"VrxInput","story":"Docs","parameters":{"__id":"vrxinput--docs","docsOnly":true,"fileName":"./src/components/VrxInput/VrxInput.stories.ts"}},"vrxinput--primary":{"id":"vrxinput--primary","title":"VrxInput","name":"Primary","importPath":"./src/components/VrxInput/VrxInput.stories.ts","tags":["autodocs","story"],"kind":"VrxInput","story":"Primary","parameters":{"__id":"vrxinput--primary","docsOnly":false,"fileName":"./src/components/VrxInput/VrxInput.stories.ts"}},"vrxinput--labeled":{"id":"vrxinput--labeled","title":"VrxInput","name":"Labeled","importPath":"./src/components/VrxInput/VrxInput.stories.ts","tags":["autodocs","story"],"kind":"VrxInput","story":"Labeled","parameters":{"__id":"vrxinput--labeled","docsOnly":false,"fileName":"./src/components/VrxInput/VrxInput.stories.ts"}},"vrxinput--icon":{"id":"vrxinput--icon","title":"VrxInput","name":"Icon","importPath":"./src/components/VrxInput/VrxInput.stories.ts","tags":["autodocs","story"],"kind":"VrxInput","story":"Icon","parameters":{"__id":"vrxinput--icon","docsOnly":false,"fileName":"./src/components/VrxInput/VrxInput.stories.ts"}},"vrxinput--password":{"id":"vrxinput--password","title":"VrxInput","name":"Password","importPath":"./src/components/VrxInput/VrxInput.stories.ts","tags":["autodocs","story"],"kind":"VrxInput","story":"Password","parameters":{"__id":"vrxinput--password","docsOnly":false,"fileName":"./src/components/VrxInput/VrxInput.stories.ts"}},"vrxinput--disabled":{"id":"vrxinput--disabled","title":"VrxInput","name":"Disabled","importPath":"./src/components/VrxInput/VrxInput.stories.ts","tags":["autodocs","story"],"kind":"VrxInput","story":"Disabled","parameters":{"__id":"vrxinput--disabled","docsOnly":false,"fileName":"./src/components/VrxInput/VrxInput.stories.ts"}},"vrxinput--invalid":{"id":"vrxinput--invalid","title":"VrxInput","name":"Invalid","importPath":"./src/components/VrxInput/VrxInput.stories.ts","tags":["autodocs","story"],"kind":"VrxInput","story":"Invalid","parameters":{"__id":"vrxinput--invalid","docsOnly":false,"fileName":"./src/components/VrxInput/VrxInput.stories.ts"}},"vrxnavbar--docs":{"id":"vrxnavbar--docs","title":"VrxNavbar","name":"Docs","importPath":"./src/components/VrxNavbar/VrxNavbar.stories.ts","tags":["autodocs","docs"],"storiesImports":[],"kind":"VrxNavbar","story":"Docs","parameters":{"__id":"vrxnavbar--docs","docsOnly":true,"fileName":"./src/components/VrxNavbar/VrxNavbar.stories.ts"}},"vrxnavbar--primary":{"id":"vrxnavbar--primary","title":"VrxNavbar","name":"Primary","importPath":"./src/components/VrxNavbar/VrxNavbar.stories.ts","tags":["autodocs","story"],"kind":"VrxNavbar","story":"Primary","parameters":{"__id":"vrxnavbar--primary","docsOnly":false,"fileName":"./src/components/VrxNavbar/VrxNavbar.stories.ts"}},"vrxselect--docs":{"id":"vrxselect--docs","title":"VrxSelect","name":"Docs","importPath":"./src/components/VrxSelect/VrxSelect.stories.ts","tags":["autodocs","docs"],"storiesImports":[],"kind":"VrxSelect","story":"Docs","parameters":{"__id":"vrxselect--docs","docsOnly":true,"fileName":"./src/components/VrxSelect/VrxSelect.stories.ts"}},"vrxselect--primary":{"id":"vrxselect--primary","title":"VrxSelect","name":"Primary","importPath":"./src/components/VrxSelect/VrxSelect.stories.ts","tags":["autodocs","story"],"kind":"VrxSelect","story":"Primary","parameters":{"__id":"vrxselect--primary","docsOnly":false,"fileName":"./src/components/VrxSelect/VrxSelect.stories.ts"}},"vrxselect--labeled":{"id":"vrxselect--labeled","title":"VrxSelect","name":"Labeled","importPath":"./src/components/VrxSelect/VrxSelect.stories.ts","tags":["autodocs","story"],"kind":"VrxSelect","story":"Labeled","parameters":{"__id":"vrxselect--labeled","docsOnly":false,"fileName":"./src/components/VrxSelect/VrxSelect.stories.ts"}},"vrxselect--selected":{"id":"vrxselect--selected","title":"VrxSelect","name":"Selected","importPath":"./src/components/VrxSelect/VrxSelect.stories.ts","tags":["autodocs","story"],"kind":"VrxSelect","story":"Selected","parameters":{"__id":"vrxselect--selected","docsOnly":false,"fileName":"./src/components/VrxSelect/VrxSelect.stories.ts"}},"vrxselect--multiselect":{"id":"vrxselect--multiselect","title":"VrxSelect","name":"Multiselect","importPath":"./src/components/VrxSelect/VrxSelect.stories.ts","tags":["autodocs","story"],"kind":"VrxSelect","story":"Multiselect","parameters":{"__id":"vrxselect--multiselect","docsOnly":false,"fileName":"./src/components/VrxSelect/VrxSelect.stories.ts"}},"vrxselect--icon":{"id":"vrxselect--icon","title":"VrxSelect","name":"Icon","importPath":"./src/components/VrxSelect/VrxSelect.stories.ts","tags":["autodocs","story"],"kind":"VrxSelect","story":"Icon","parameters":{"__id":"vrxselect--icon","docsOnly":false,"fileName":"./src/components/VrxSelect/VrxSelect.stories.ts"}},"vrxselect--disabled":{"id":"vrxselect--disabled","title":"VrxSelect","name":"Disabled","importPath":"./src/components/VrxSelect/VrxSelect.stories.ts","tags":["autodocs","story"],"kind":"VrxSelect","story":"Disabled","parameters":{"__id":"vrxselect--disabled","docsOnly":false,"fileName":"./src/components/VrxSelect/VrxSelect.stories.ts"}},"vrxselect--invalid":{"id":"vrxselect--invalid","title":"VrxSelect","name":"Invalid","importPath":"./src/components/VrxSelect/VrxSelect.stories.ts","tags":["autodocs","story"],"kind":"VrxSelect","story":"Invalid","parameters":{"__id":"vrxselect--invalid","docsOnly":false,"fileName":"./src/components/VrxSelect/VrxSelect.stories.ts"}},"vrxselect--variant":{"id":"vrxselect--variant","title":"VrxSelect","name":"Variant","importPath":"./src/components/VrxSelect/VrxSelect.stories.ts","tags":["autodocs","story"],"kind":"VrxSelect","story":"Variant","parameters":{"__id":"vrxselect--variant","docsOnly":false,"fileName":"./src/components/VrxSelect/VrxSelect.stories.ts"}},"vrxtoggle--docs":{"id":"vrxtoggle--docs","title":"VrxToggle","name":"Docs","importPath":"./src/components/VrxToggle/VrxToggle.stories.ts","tags":["autodocs","docs"],"storiesImports":[],"kind":"VrxToggle","story":"Docs","parameters":{"__id":"vrxtoggle--docs","docsOnly":true,"fileName":"./src/components/VrxToggle/VrxToggle.stories.ts"}},"vrxtoggle--primary":{"id":"vrxtoggle--primary","title":"VrxToggle","name":"Primary","importPath":"./src/components/VrxToggle/VrxToggle.stories.ts","tags":["autodocs","story"],"kind":"VrxToggle","story":"Primary","parameters":{"__id":"vrxtoggle--primary","docsOnly":false,"fileName":"./src/components/VrxToggle/VrxToggle.stories.ts"}},"vrxtoggle--size":{"id":"vrxtoggle--size","title":"VrxToggle","name":"Size","importPath":"./src/components/VrxToggle/VrxToggle.stories.ts","tags":["autodocs","story"],"kind":"VrxToggle","story":"Size","parameters":{"__id":"vrxtoggle--size","docsOnly":false,"fileName":"./src/components/VrxToggle/VrxToggle.stories.ts"}},"vrxtoggle--variants":{"id":"vrxtoggle--variants","title":"VrxToggle","name":"Variants","importPath":"./src/components/VrxToggle/VrxToggle.stories.ts","tags":["autodocs","story"],"kind":"VrxToggle","story":"Variants","parameters":{"__id":"vrxtoggle--variants","docsOnly":false,"fileName":"./src/components/VrxToggle/VrxToggle.stories.ts"}},"foundations-colors--colors":{"id":"foundations-colors--colors","title":"Foundations/Colors","name":"Colors","importPath":"./node_modules/storybook-tailwind-foundations/src/stories/Colors.stories.js","tags":["story"],"kind":"Foundations/Colors","story":"Colors","parameters":{"__id":"foundations-colors--colors","docsOnly":false,"fileName":"./node_modules/storybook-tailwind-foundations/src/stories/Colors.stories.js"}},"foundations-screens--screens":{"id":"foundations-screens--screens","title":"Foundations/Screens","name":"Screens","importPath":"./node_modules/storybook-tailwind-foundations/src/stories/Screens.stories.js","tags":["story"],"kind":"Foundations/Screens","story":"Screens","parameters":{"__id":"foundations-screens--screens","docsOnly":false,"fileName":"./node_modules/storybook-tailwind-foundations/src/stories/Screens.stories.js"}},"foundations-spaces--spaces":{"id":"foundations-spaces--spaces","title":"Foundations/Spaces","name":"Spaces","importPath":"./node_modules/storybook-tailwind-foundations/src/stories/Spaces.stories.js","tags":["story"],"kind":"Foundations/Spaces","story":"Spaces","parameters":{"__id":"foundations-spaces--spaces","docsOnly":false,"fileName":"./node_modules/storybook-tailwind-foundations/src/stories/Spaces.stories.js"}}}}
